README.rst
setup.py
icecake/__init__.py
icecake/cli.py
icecake/livejs.py
icecake/templates.py
icecake.egg-info/PKG-INFO
icecake.egg-info/SOURCES.txt
icecake.egg-info/dependency_links.txt
icecake.egg-info/entry_points.txt
icecake.egg-info/requires.txt
icecake.egg-info/top_level.txt
test/test_icecake.py