Metadata-Version: 1.1
Name: icecake
Version: 0.6.1
Summary: An easy and cool static site generator
Home-page: https://github.com/cbednarski/icecake
Author: Chris Bednarski
Author-email: chris@cbednarski.com
License: MIT
Keywords: static site generator builder icecake
Platform: UNKNOWN
Classifier: Development Status :: 4 - Beta
Classifier: Intended Audience :: Developers
Classifier: License :: OSI Approved :: MIT License
Classifier: Operating System :: OS Independent
Classifier: Programming Language :: Python
Classifier: Programming Language :: Python :: 2.7
Classifier: Programming Language :: Python :: 3.6
